{
	"configurations" : 
	[
		{
			"directories" : 
			[
				{
					"build" : ".",
					"jsonFile" : "directory-.-Debug-f5ebdc15457944623624.json",
					"minimumCMakeVersion" : 
					{
						"string" : "3.0"
					},
					"projectIndex" : 0,
					"source" : ".",
					"targetIndexes" : 
					[
						0
					]
				}
			],
			"name" : "Debug",
			"projects" : 
			[
				{
					"directoryIndexes" : 
					[
						0
					],
					"name" : "3D_model",
					"targetIndexes" : 
					[
						0
					]
				}
			],
			"targets" : 
			[
				{
					"directoryIndex" : 0,
					"id" : "3D_model::@6890427a1f51a3e7e1df",
					"jsonFile" : "target-3D_model-Debug-df8fb53b3cf03b64cde9.json",
					"name" : "3D_model",
					"projectIndex" : 0
				}
			]
		}
	],
	"kind" : "codemodel",
	"paths" : 
	{
		"build" : "/home/pavel_ignatev/Project_3DModel-main/build",
		"source" : "/home/pavel_ignatev/Project_3DModel-main"
	},
	"version" : 
	{
		"major" : 2,
		"minor" : 3
	}
}
